{
    "@class": "com.kony.gen.viz.model.component.KVizLabel",
    "DNDConfig": null,
    "_bottom_": {
        "type": "string",
        "value": "0"
    },
    "_height_": {
        "type": "string",
        "value": "50%"
    },
    "_margin_": [
        1,
        1,
        1,
        1
    ],
    "_padding_": [
        0,
        0,
        0,
        0
    ],
    "_right_": {
        "type": "string",
        "value": "0"
    },
    "_skin_": "sb3b7267feb14d07bec0018edbc72ad1",
    "_text_": "MAR",
    "_width_": {
        "type": "string",
        "value": "92.31%"
    },
    "_wrapping_": 2,
    "android": {
        "textStyle": {
            "letterSpacing": 0,
            "strikeThrough": false
        }
    },
    "canUpdateUI": true,
    "centerx": {
        "type": "string",
        "value": "50.00%"
    },
    "centery": {
        "type": "string",
        "value": "65%"
    },
    "containerweight": 100,
    "contentalignment": 8,
    "id": "lblTicketMuseu1",
    "info": null,
    "ipad": {
        "psp": {
            "wrapping": 2
        }
    },
    "iphone": {
        "psp": {
            "wrapping": 2
        }
    },
    "iscustomlayout": false,
    "isvisible": true,
    "kuid": "b7847baf70de4bb9a6d7c0058b83b859",
    "name": "kony.ui.Label",
    "parent": "flxMuseumTicket1",
    "pf": "frmDashboard",
    "retaincontentalignment": false,
    "retainflexpositionproperties": false,
    "textstyle": {},
    "tooltip": "",
    "wType": "Label",
    "zindex": 1
}